network_layer/__init__.py
network_layer/network/__init__.py
network_layer/network/client.py
network_layer/network/endpoint.py
network_layer/network/exceptions.py
network_layer/network/logger.py
network_layer-0.1.0.dist-info/LICENSE
network_layer-0.1.0.dist-info/METADATA
network_layer-0.1.0.dist-info/WHEEL
network_layer-0.1.0.dist-info/RECORD
