Metadata-Version: 2.1
Name: network-layer
Version: 0.1.0
Summary: A reusable network kit for dynamic API requests.
License: MIT
Author: Alhatoon Algarni
Author-email: alhatoon.algarni@mobily.com.sa
Requires-Python: >=3.11,<4.0
Classifier: License :: OSI Approved :: MIT License
Classifier: Programming Language :: Python :: 3
Classifier: Programming Language :: Python :: 3.11
Classifier: Programming Language :: Python :: 3.12
Classifier: Programming Language :: Python :: 3.13
Requires-Dist: httpx (>=0.28.1,<0.29.0)
Requires-Dist: structlog (>=24.4.0,<25.0.0)
Requires-Dist: tenacity (>=9.0.0,<10.0.0)
